[
 {
  "id":"1",
  "name":"Vehicle",
  "parent_id":"0"
 }, 
 {
  "id":"2",
  "name":"Pet",
  "parent_id":"0"
 }, 
 {
  "id":"3",
  "name":"Book",
  "parent_id":"0"
 }, 
 {
  "id":"4",
  "name":"Phone",
  "parent_id":"0"
 }, 
 {
  "id":"5",
  "name":"Computer",
  "parent_id":"0"
 }, 
 {
  "id":"6",
  "name":"Instrument",
  "parent_id":"0"
 }, 
 {
  "id":"7",
  "name":"Bike",
  "parent_id":"0"
 }, 
 {
  "id":"8",
  "name":"TV",
  "parent_id":"0"
 }, 
 {
  "id":"9",
  "name":"Sedan",
  "parent_id":"1"
 }, 
 {
  "id":"10",
  "name":"SUV",
  "parent_id":"1"
 }, 
 {
  "id":"11",
  "name":"Pickup Truck",
  "parent_id":"1"
 }, 
 {
  "id":"12",
  "name":"Van",
  "parent_id":"1"
 }, 
 {
  "id":"13",
  "name":"Dog",
  "parent_id":"2"
 }, 
 {
  "id":"14",
  "name":"Bird",
  "parent_id":"2"
 }, 
 {
  "id":"15",
  "name":"Cat",
  "parent_id":"2"
 }, 
 {
  "id":"16",
  "name":"Textbook",
  "parent_id":"3"
 }, 
 {
  "id":"17",
  "name":"Cookbook",
  "parent_id":"3"
 }, 
 {
  "id":"18",
  "name":"Fiction",
  "parent_id":"3"
 }, 
 {
  "id":"19",
  "name":"Dictionary",
  "parent_id":"3"
 }, 
 {
  "id":"20",
  "name":"Telephone",
  "parent_id":"4"
 }, 
 {
  "id":"21",
  "name":"Smart phone",
  "parent_id":"4"
 }, 
 {
  "id":"22",
  "name":"Desk Computer",
  "parent_id":"5"
 }, 
 {
  "id":"23",
  "name":"Laptop",
  "parent_id":"5"
 }, 
 {
  "id":"24",
  "name":"Guitars",
  "parent_id":"6"
 }, 
 {
  "id":"25",
  "name":"Piano",
  "parent_id":"6"
 }, 
 {
  "id":"26",
  "name":"Drum",
  "parent_id":"6"
 }, 
 {
  "id":"27",
  "name":"Bike in road",
  "parent_id":"7"
 },
 {
  "id":"28",
  "name":"Bike in mountain",
  "parent_id":"7"
 },
 {
  "id":"29",
  "name":"LED",
  "parent_id":"8"
 },
 {
  "id":"30",
  "name":"4K UHD",
  "parent_id":"8"
 },
 {
  "id":"31",
  "name":"BMW",
  "parent_id":"9"
 },
 {
  "id":"32",
  "name":"Audi",
  "parent_id":"9"
 },
 {
  "id":"33",
  "name":"Volvo",
  "parent_id":"9"
 },
 {
  "id":"34",
  "name":"Toyota",
  "parent_id":"9"
 },
 {
  "id":"35",
  "name":"Honda",
  "parent_id":"9"
 },
 {
  "id":"36",
  "name":"Ford",
  "parent_id":"9"
 },
 {
  "id":"37",
  "name":"Nissan",
  "parent_id":"9"
 },
  {
  "id":"38",
  "name":"Porsche",
  "parent_id":"10"
 }, 
 {
  "id":"39",
  "name":"LandRover",
  "parent_id":"10"
 }, 
 {
  "id":"40",
  "name":"Audi",
  "parent_id":"10"
 }, 
 {
  "id":"41",
  "name":"BMW",
  "parent_id":"10"
 }, 
 {
  "id":"42",
  "name":"Volvo",
  "parent_id":"10"
 }, 
 {
  "id":"43",
  "name":"Dodge RAM",
  "parent_id":"11"
 }, 
 {
  "id":"44",
  "name":"Ford",
  "parent_id":"11"
 }, 
 {
  "id":"45",
  "name":"Toyota Titan",
  "parent_id":"11"
 }, 
 {
  "id":"46",
  "name":"Dodge Caravan",
  "parent_id":"12"
 }, 
 {
  "id":"47",
  "name":"Nissan Sentra",
  "parent_id":"12"
 }, 
 {
  "id":"48",
  "name":"Honda Odyssey",
  "parent_id":"12"
 }, 
 {
  "id":"49",
  "name":"pug",
  "parent_id":"13"
 }, 
 {
  "id":"50",
  "name":"chihuahua",
  "parent_id":"13"
 }, 
 {
  "id":"51",
  "name":"yorkshire",
  "parent_id":"13"
 }, 
 {
  "id":"52",
  "name":"perroquet",
  "parent_id":"14"
 }, 
 {
  "id":"53",
  "name":"canari",
  "parent_id":"14"
 }, 
 {
  "id":"54",
  "name":"cockatiel",
  "parent_id":"14"
 }, 
 {
  "id":"55",
  "name":"bengal",
  "parent_id":"15"
 }, 
 {
  "id":"56",
  "name":"persian",
  "parent_id":"15"
 }, 
 {
  "id":"57",
  "name":"Accounting",
  "parent_id":"16"
 }, 
 {
  "id":"58",
  "name":"Computer",
  "parent_id":"16"
 }, 
 {
  "id":"59",
  "name":"History",
  "parent_id":"16"
 }, 
 {
  "id":"60",
  "name":"Nursing",
  "parent_id":"16"
 }, 
 {
  "id":"61",
  "name":"Baking",
  "parent_id":"17"
 }, 
 {
  "id":"62",
  "name":"Meals",
  "parent_id":"17"
 }, 
 {
  "id":"63",
  "name":"Quick and Easy",
  "parent_id":"17"
 }, 
 {
  "id":"64",
  "name":"Fantasy",
  "parent_id":"18"
 },
 {
  "id":"65",
  "name":"Science Fiction",
  "parent_id":"18"
 },
 {
  "id":"66",
  "name":"Gaming",
  "parent_id":"18"
 },
 {
  "id":"67",
  "name":"English-English",
  "parent_id":"19"
 },
 {
  "id":"68",
  "name":"English-Chinese",
  "parent_id":"19"
 },
 {
  "id":"69",
  "name":"French-Chinese",
  "parent_id":"19"
 },
 {
  "id":"70",
  "name":"Samsung",
  "parent_id":"20"
 },
 {
  "id":"71",
  "name":"LG",
  "parent_id":"20"
 },
 {
  "id":"72",
  "name":"Iphone",
  "parent_id":"21"
 },
 {
  "id":"73",
  "name":"Samsung",
  "parent_id":"21"
 },
 {
  "id":"74",
  "name":"Nokia",
  "parent_id":"21"
 },
  {
  "id":"75",
  "name":"Black Berry",
  "parent_id":"21"
 },
 {
  "id":"76",
  "name":"Dell",
  "parent_id":"22"
 }, 
 {
  "id":"77",
  "name":"HP",
  "parent_id":"22"
 }, 
 {
  "id":"78",
  "name":"Lenovo",
  "parent_id":"22"
 }, 
 {
  "id":"79",
  "name":"Macbook Pro",
  "parent_id":"23"
 }, 
 {
  "id":"80",
  "name":"Macbook Air",
  "parent_id":"23"
 }, 
 {
  "id":"81",
  "name":"Thinkpad",
  "parent_id":"23"
 }, 
 {
  "id":"82",
  "name":"Electric Guitar",
  "parent_id":"24"
 },
 {
  "id":"83",
  "name":"Acoustic Guitar",
  "parent_id":"24"
 },
 {
  "id":"84",
  "name":"Base Guitar",
  "parent_id":"24"
 },
 {
  "id":"85",
  "name":"Classic Piano",
  "parent_id":"25"
 },
 {
  "id":"86",
  "name":"Electric Piano",
  "parent_id":"25"
 },
 {
  "id":"87",
  "name":"Mute Piano",
  "parent_id":"25"
 },
 {
  "id":"88",
  "name":"Jazz Drum",
  "parent_id":"26"
 },
 {
  "id":"89",
  "name":"Electric Drum",
  "parent_id":"26"
 },
 {
  "id":"90",
  "name":"Classic Drum",
  "parent_id":"26"
 },
 {
  "id":"91",
  "name":"Felt VR30",
  "parent_id":"27"
 },
 {
  "id":"92",
  "name":"Felt Z6 Disc",
  "parent_id":"27"
 },
 {
  "id":"93",
  "name":"Devinci Leo SL",
  "parent_id":"27"
 },
 {
  "id":"94",
  "name":"Devinci Troy",
  "parent_id":"28"
 },
 {
  "id":"95",
  "name":"Rock Mountain Pipeline",
  "parent_id":"28"
 },
 {
  "id":"96",
  "name":"Giant Iguana",
  "parent_id":"28"
 },
  {
  "id":"97",
  "name":"SONY",
  "parent_id":"29"
 },
 {
  "id":"98",
  "name":"SHARP",
  "parent_id":"29"
 },
 {
  "id":"99",
  "name":"SAMSUNG",
  "parent_id":"29"
 },
 {
  "id":"100",
  "name":"SONY",
  "parent_id":"30"
 },
 {
  "id":"101",
  "name":"SHARP",
  "parent_id":"30"
 },
 {
  "id":"102",
  "name":"SAMSUNG",
  "parent_id":"30"
 }
]